tikzification/__about__.py
tikzification/__init__.py
tikzification/_axes.py
tikzification/_cleanfigure.py
tikzification/_color.py
tikzification/_config.py
tikzification/_files.py
tikzification/_hatches.py
tikzification/_image.py
tikzification/_legend.py
tikzification/_line2d.py
tikzification/_markers.py
tikzification/_patch.py
tikzification/_path.py
tikzification/_quadmesh.py
tikzification/_save.py
tikzification/_text.py
tikzification/_util.py
tikzification-0.0.2.dist-info/LICENSE
tikzification-0.0.2.dist-info/WHEEL
tikzification-0.0.2.dist-info/METADATA
tikzification-0.0.2.dist-info/RECORD
